zenx/__init__.py
zenx/zenx.py
zenx-1.0.5.dist-info/METADATA
zenx-1.0.5.dist-info/WHEEL
zenx-1.0.5.dist-info/top_level.txt
zenx-1.0.5.dist-info/RECORD
